MANIFEST.in
README.rst
requirements.txt
setup.py
test-requirements.txt
tests/__init__.py
tests/test_client.py
tests/test_uri.py
tests/test_utils.py
zaif/__init__.py
zaif/client.py
zaif/compat.py
zaif/errors.py
zaif/uri.py
zaif/utils.py
zaif.egg-info/PKG-INFO
zaif.egg-info/SOURCES.txt
zaif.egg-info/dependency_links.txt
zaif.egg-info/requires.txt
zaif.egg-info/top_level.txt