Metadata-Version: 1.1
Name: zaif
Version: 1.0.0
Summary: Zaif API library
Home-page: https://github.com/pulkit1991/zaif
Author: Pulkit Gupta
Author-email: gupta.pulkit91@gmail.com
License: MIT
Download-URL: https://github.com/pulkit1991/zaif/tarball/1.0.0
Keywords: zaif,api,client,bitcoin,altcoin,trading
Platform: UNKNOWN
Classifier: Intended Audience :: Developers
Classifier: License :: OSI Approved :: MIT License
Classifier: Operating System :: OS Independent
Classifier: Programming Language :: Python :: 2
Classifier: Programming Language :: Python :: 2.7
Classifier: Programming Language :: Python :: 3.4
Classifier: Programming Language :: Python :: 3.5
Classifier: Programming Language :: Python :: 3.6
Classifier: Programming Language :: Python
Classifier: Topic :: Software Development :: Libraries :: Python Modules
